[
  {
    "contractor_name": "Jane Smith",
    "contractor_address": "123 Main St",
    "contractor_city": "Toronto",
    "contractor_state": "ON",
    "contractor_zip": "M5H 2N2",
    "contractor_phone": "416-555-1234",
    "contractor_email": "jane.smith@example.com"
  },
  {
    "contractor_name": "John Doe",
    "contractor_address": "456 Robson St",
    "contractor_city": "Vancouver",
    "contractor_state": "BC",
    "contractor_zip": "V6B 2B2",
    "contractor_phone": "604-555-5678",
    "contractor_email": "john.doe@example.com"
  },
  {
    "contractor_name": "Lisa Marshall",
    "contractor_address": "789 Rideau St",
    "contractor_city": "Ottawa",
    "contractor_state": "ON",
    "contractor_zip": "K1N 5X9",
    "contractor_phone": "613-555-9012",
    "contractor_email": "lisa.marshall@example.com"
  }
]
